{"cameraMode":{"drawMode":0,"name":"Shaded","section":"Shading Mode"},"sceneLighting":false,"audioPlay":false,"sceneViewState":{"m_AlwaysRefresh":false,"showFog":true,"showSkybox":true,"showFlares":true,"showImageEffects":true,"showParticleSystems":true,"showVisualEffectGraphs":true,"m_FxEnabled":true},"in2DMode":false,"pivot":{"x":-2.0519933700561525,"y":46.473289489746097,"z":-64.72785949707031},"rotation":{"x":0.1240316703915596,"y":-0.4368751049041748,"z":0.06023714318871498,"w":0.8890097141265869},"size":0.8660253882408142,"orthographic":false}